img2pdfscrpr/__init__.py
img2pdfscrpr/__main__.py
img2pdfscrpr/img2pdfscrpr.py
img2pdfscrpr-0.1.dist-info/entry_points.txt
img2pdfscrpr-0.1.dist-info/WHEEL
img2pdfscrpr-0.1.dist-info/METADATA
img2pdfscrpr-0.1.dist-info/RECORD
